[{"source":"R","target":"S","relationship":"first"},{"source":"R","target":"C","relationship":"first"},{"source":"R","target":"APL","relationship":"first"},{"source":"R","target":"MATLAB","relationship":"first"},{"source":"R","target":"SPSS","relationship":"first"},{"source":"C","target":"B","relationship":"second"},{"source":"C","target":"BCPL","relationship":"second"},{"source":"C","target":"CPL","relationship":"second"},{"source":"C","target":"AMPL","relationship":"second"},{"source":"C","target":"C--","relationship":"second"},{"source":"C","target":"D","relationship":"second"},{"source":"C","target":"LPC","relationship":"second"},{"source":"C","target":"PHP","relationship":"second"},{"source":"C","target":"MATLAB","relationship":"second"},{"source":"MATLAB","target":"MATHLAB","relationship":"second"},{"source":"MATLAB","target":"C","relationship":"second"},{"source":"MATLAB","target":"APL","relationship":"second"},{"source":"MATLAB","target":"IDL","relationship":"second"},{"source":"MATLAB","target":"S","relationship":"second"},{"source":"APL","target":"APLX","relationship":"second"},{"source":"APL","target":"J","relationship":"second"},{"source":"APL","target":"K","relationship":"second"},{"source":"APL","target":"MATLAB","relationship":"second"},{"source":"APL","target":"Q","relationship":"second"},{"source":"APL","target":"S","relationship":"second"},{"source":"APL","target":"BASIC","relationship":"second"},{"source":"APL","target":"COBOL","relationship":"second"},{"source":"APL","target":"C","relationship":"second"},{"source":"APL","target":"CIL","relationship":"second"},{"source":"APL","target":"RPL","relationship":"second"},{"source":"S","target":"S-PLUS","relationship":"second"},{"source":"S","target":"C","relationship":"second"},{"source":"S","target":"APL","relationship":"second"}]
